[
  {
    "Message": "Library with id '' was not found.",
    "Level": "Error",
    "Reason": "NotFound",
    "Category": "Component",
    "Context": {
      "ComponentId": null,
      "ViewId": null
    },
    "UTCTimestamp": "2025-05-15T08:27:53.9454299Z"
  },
  {
    "Message": "Missing definition id!",
    "Level": "Error",
    "Reason": "NotFound",
    "Category": "Component",
    "Context": {
      "ComponentId": null,
      "ViewId": null
    },
    "UTCTimestamp": "2025-05-15T08:27:53.9454317Z"
  },
  {
    "Message": "Library with id '' was not found.",
    "Level": "Error",
    "Reason": "NotFound",
    "Category": "Component",
    "Context": {
      "ComponentId": null,
      "ViewId": null
    },
    "UTCTimestamp": "2025-05-15T08:27:53.9454795Z"
  },
  {
    "Message": "Missing definition id!",
    "Level": "Error",
    "Reason": "NotFound",
    "Category": "Component",
    "Context": {
      "ComponentId": null,
      "ViewId": null
    },
    "UTCTimestamp": "2025-05-15T08:27:53.9454799Z"
  },
  {
    "Message": "Library with id '' was not found.",
    "Level": "Error",
    "Reason": "NotFound",
    "Category": "Component",
    "Context": {
      "ComponentId": null,
      "ViewId": null
    },
    "UTCTimestamp": "2025-05-15T08:27:53.9468422Z"
  },
  {
    "Message": "Missing definition id!",
    "Level": "Error",
    "Reason": "NotFound",
    "Category": "Component",
    "Context": {
      "ComponentId": null,
      "ViewId": null
    },
    "UTCTimestamp": "2025-05-15T08:27:53.9468436Z"
  },
  {
    "Message": "Library with id '' was not found.",
    "Level": "Error",
    "Reason": "NotFound",
    "Category": "Component",
    "Context": {
      "ComponentId": null,
      "ViewId": null
    },
    "UTCTimestamp": "2025-05-15T08:27:53.9468871Z"
  },
  {
    "Message": "Missing definition id!",
    "Level": "Error",
    "Reason": "NotFound",
    "Category": "Component",
    "Context": {
      "ComponentId": null,
      "ViewId": null
    },
    "UTCTimestamp": "2025-05-15T08:27:53.9468875Z"
  },
  {
    "Message": "Library with id '' was not found.",
    "Level": "Error",
    "Reason": "NotFound",
    "Category": "Component",
    "Context": {
      "ComponentId": null,
      "ViewId": null
    },
    "UTCTimestamp": "2025-05-15T08:27:53.9479985Z"
  },
  {
    "Message": "Missing definition id!",
    "Level": "Error",
    "Reason": "NotFound",
    "Category": "Component",
    "Context": {
      "ComponentId": null,
      "ViewId": null
    },
    "UTCTimestamp": "2025-05-15T08:27:53.948Z"
  },
  {
    "Message": "Library with id '' was not found.",
    "Level": "Error",
    "Reason": "NotFound",
    "Category": "Component",
    "Context": {
      "ComponentId": null,
      "ViewId": null
    },
    "UTCTimestamp": "2025-05-15T08:27:53.9480418Z"
  },
  {
    "Message": "Missing definition id!",
    "Level": "Error",
    "Reason": "NotFound",
    "Category": "Component",
    "Context": {
      "ComponentId": null,
      "ViewId": null
    },
    "UTCTimestamp": "2025-05-15T08:27:53.9480422Z"
  }
]